{"Meta Data": {"1. Information": "Intraday (60min) open, high, low, close prices and volume", "2. Symbol": "GME", "3. Last Refreshed": "2023-11-24 17:00:00", "4. Interval": "60min", "5. Output Size": "Full size", "6. Time Zone": "US/Eastern"}, "Time Series (60min)": {"2023-11-24 17:00:00": {"1. open": "12.2000", "2. high": "12.2000", "3. low": "12.2000", "4. close": "12.2000", "5. volume": "64882"}, "2023-11-24 16:00:00": {"1. open": "12.2900", "2. high": "12.3000", "3. low": "12.2200", "4. close": "12.2800", "5. volume": "1905"}, "2023-11-24 15:00:00": {"1. open": "12.2480", "2. high": "12.3000", "3. low": "12.2000", "4. close": "12.2600", "5. volume": "66116"}, "2023-11-24 14:00:00": {"1. open": "12.2500", "2. high": "12.2500", "3. low": "12.2000", "4. close": "12.2300", "5. volume": "1322"}, "2023-11-24 13:00:00": {"1. open": "12.2150", "2. high": "12.3100", "3. low": "12.2000", "4. close": "12.2200", "5. volume": "204044"}, "2023-11-24 12:00:00": {"1. open": "12.2700", "2. high": "12.3100", "3. low": "12.2100", "4. close": "12.2100", "5. volume": "388090"}, "2023-11-24 11:00:00": {"1. open": "12.3700", "2. high": "12.4100", "3. low": "12.2700", "4. close": "12.2800", "5. volume": "232971"}, "2023-11-24 10:00:00": {"1. open": "12.2300", "2. high": "12.3850", "3. low": "12.2300", "4. close": "12.3750", "5. volume": "307238"}, "2023-11-24 09:00:00": {"1. open": "12.3100", "2. high": "12.3400", "3. low": "12.1750", "4. close": "12.2310", "5. volume": "208574"}, "2023-11-24 08:00:00": {"1. open": "12.3750", "2. high": "12.4900", "3. low": "12.2900", "4. close": "12.3200", "5. volume": "12152"}, "2023-11-24 07:00:00": {"1. open": "12.3500", "2. high": "12.3700", "3. low": "12.3200", "4. close": "12.3200", "5. volume": "3414"}, "2023-11-24 06:00:00": {"1. open": "12.3800", "2. high": "12.3900", "3. low": "12.3500", "4. close": "12.3700", "5. volume": "507"}, "2023-11-24 05:00:00": {"1. open": "12.3700", "2. high": "12.4400", "3. low": "12.3200", "4. close": "12.3500", "5. volume": "947"}, "2023-11-24 04:00:00": {"1. open": "12.5500", "2. high": "12.5500", "3. low": "12.2500", "4. close": "12.4100", "5. volume": "448"}, "2023-11-22 19:00:00": {"1. open": "12.2900", "2. high": "12.3100", "3. low": "12.2500", "4. close": "12.2500", "5. volume": "130462"}, "2023-11-22 18:00:00": {"1. open": "12.3000", "2. high": "12.3100", "3. low": "12.2500", "4. close": "12.2700", "5. volume": "127593"}, "2023-11-22 17:00:00": {"1. open": "12.2900", "2. high": "12.3100", "3. low": "12.2500", "4. close": "12.2900", "5. volume": "8246"}, "2023-11-22 16:00:00": {"1. open": "12.2850", "2. high": "12.3300", "3. low": "12.2700", "4. close": "12.2800", "5. volume": "391762"}, "2023-11-22 15:00:00": {"1. open": "12.2300", "2. high": "12.3100", "3. low": "12.2050", "4. close": "12.2800", "5. volume": "544888"}, "2023-11-22 14:00:00": {"1. open": "12.3700", "2. high": "12.3800", "3. low": "12.1900", "4. close": "12.2400", "5. volume": "544692"}, "2023-11-22 13:00:00": {"1. open": "12.4550", "2. high": "12.4900", "3. low": "12.3750", "4. close": "12.3750", "5. volume": "193887"}, "2023-11-22 12:00:00": {"1. open": "12.5100", "2. high": "12.5600", "3. low": "12.4550", "4. close": "12.4550", "5. volume": "188803"}, "2023-11-22 11:00:00": {"1. open": "12.5800", "2. high": "12.5950", "3. low": "12.4550", "4. close": "12.5200", "5. volume": "193983"}, "2023-11-22 10:00:00": {"1. open": "12.5700", "2. high": "12.7100", "3. low": "12.5400", "4. close": "12.5760", "5. volume": "303148"}, "2023-11-22 09:00:00": {"1. open": "12.5900", "2. high": "12.6900", "3. low": "12.4150", "4. close": "12.5650", "5. volume": "234984"}, "2023-11-22 08:00:00": {"1. open": "12.6600", "2. high": "12.7500", "3. low": "12.5000", "4. close": "12.5900", "5. volume": "6701"}, "2023-11-22 07:00:00": {"1. open": "12.6400", "2. high": "12.6600", "3. low": "12.5900", "4. close": "12.6500", "5. volume": "755"}, "2023-11-22 06:00:00": {"1. open": "12.6000", "2. high": "12.6500", "3. low": "12.6000", "4. close": "12.6500", "5. volume": "153"}, "2023-11-22 05:00:00": {"1. open": "12.5800", "2. high": "12.6000", "3. low": "12.5800", "4. close": "12.5900", "5. volume": "216"}, "2023-11-22 04:00:00": {"1. open": "12.4900", "2. high": "12.5900", "3. low": "12.4900", "4. close": "12.5800", "5. volume": "421"}, "2023-11-21 19:00:00": {"1. open": "12.5500", "2. high": "12.5500", "3. low": "12.4900", "4. close": "12.4900", "5. volume": "273646"}, "2023-11-21 18:00:00": {"1. open": "12.5300", "2. high": "12.5600", "3. low": "12.4600", "4. close": "12.5600", "5. volume": "273470"}, "2023-11-21 17:00:00": {"1. open": "12.5500", "2. high": "12.5600", "3. low": "12.5100", "4. close": "12.5400", "5. volume": "4212"}, "2023-11-21 16:00:00": {"1. open": "12.5600", "2. high": "12.6000", "3. low": "12.5100", "4. close": "12.5300", "5. volume": "827123"}, "2023-11-21 15:00:00": {"1. open": "12.5700", "2. high": "12.6000", "3. low": "12.4900", "4. close": "12.5600", "5. volume": "623940"}, "2023-11-21 14:00:00": {"1. open": "12.4350", "2. high": "12.5800", "3. low": "12.4300", "4. close": "12.5700", "5. volume": "269135"}, "2023-11-21 13:00:00": {"1. open": "12.3150", "2. high": "12.4500", "3. low": "12.2800", "4. close": "12.4380", "5. volume": "343366"}, "2023-11-21 12:00:00": {"1. open": "12.3350", "2. high": "12.3400", "3. low": "12.2600", "4. close": "12.3200", "5. volume": "453599"}, "2023-11-21 11:00:00": {"1. open": "12.3650", "2. high": "12.4800", "3. low": "12.3150", "4. close": "12.3350", "5. volume": "530460"}, "2023-11-21 10:00:00": {"1. open": "12.3650", "2. high": "12.4370", "3. low": "12.2550", "4. close": "12.3650", "5. volume": "616113"}, "2023-11-21 09:00:00": {"1. open": "12.7800", "2. high": "12.8100", "3. low": "12.2900", "4. close": "12.3700", "5. volume": "572472"}, "2023-11-21 08:00:00": {"1. open": "12.9580", "2. high": "12.9800", "3. low": "12.7500", "4. close": "12.8200", "5. volume": "5017"}, "2023-11-21 07:00:00": {"1. open": "12.9500", "2. high": "12.9600", "3. low": "12.8100", "4. close": "12.8200", "5. volume": "2440"}, "2023-11-21 06:00:00": {"1. open": "12.9300", "2. high": "12.9400", "3. low": "12.8400", "4. close": "12.8700", "5. volume": "379"}, "2023-11-21 05:00:00": {"1. open": "12.9500", "2. high": "12.9800", "3. low": "12.8500", "4. close": "12.9300", "5. volume": "823"}, "2023-11-21 04:00:00": {"1. open": "13.0000", "2. high": "13.0000", "3. low": "12.7500", "4. close": "12.8500", "5. volume": "621"}, "2023-11-20 19:00:00": {"1. open": "12.8000", "2. high": "12.8300", "3. low": "12.7600", "4. close": "12.8300", "5. volume": "170834"}, "2023-11-20 18:00:00": {"1. open": "12.8000", "2. high": "12.8300", "3. low": "12.7800", "4. close": "12.8000", "5. volume": "166156"}, "2023-11-20 17:00:00": {"1. open": "12.8200", "2. high": "12.8300", "3. low": "12.7800", "4. close": "12.8300", "5. volume": "4031"}, "2023-11-20 16:00:00": {"1. open": "12.8000", "2. high": "12.8600", "3. low": "12.8000", "4. close": "12.8300", "5. volume": "518377"}, "2023-11-20 15:00:00": {"1. open": "12.9210", "2. high": "12.9210", "3. low": "12.8000", "4. close": "12.8000", "5. volume": "472986"}, "2023-11-20 14:00:00": {"1. open": "12.9350", "2. high": "12.9900", "3. low": "12.9150", "4. close": "12.9200", "5. volume": "198371"}, "2023-11-20 13:00:00": {"1. open": "13.0550", "2. high": "13.0900", "3. low": "12.9300", "4. close": "12.9300", "5. volume": "220881"}, "2023-11-20 12:00:00": {"1. open": "13.0500", "2. high": "13.1300", "3. low": "13.0350", "4. close": "13.0550", "5. volume": "253790"}, "2023-11-20 11:00:00": {"1. open": "13.1600", "2. high": "13.1750", "3. low": "13.0380", "4. close": "13.0400", "5. volume": "197608"}, "2023-11-20 10:00:00": {"1. open": "13.0410", "2. high": "13.2000", "3. low": "12.9800", "4. close": "13.1600", "5. volume": "447649"}, "2023-11-20 09:00:00": {"1. open": "13.0300", "2. high": "13.1600", "3. low": "12.8100", "4. close": "13.0400", "5. volume": "298489"}, "2023-11-20 08:00:00": {"1. open": "13.0900", "2. high": "13.1000", "3. low": "13.0300", "4. close": "13.0900", "5. volume": "11408"}, "2023-11-20 07:00:00": {"1. open": "13.0700", "2. high": "13.1000", "3. low": "13.0300", "4. close": "13.0500", "5. volume": "2067"}, "2023-11-20 06:00:00": {"1. open": "13.0900", "2. high": "13.0900", "3. low": "13.0600", "4. close": "13.0800", "5. volume": "152"}, "2023-11-20 05:00:00": {"1. open": "13.0900", "2. high": "13.0900", "3. low": "13.0600", "4. close": "13.0900", "5. volume": "123"}, "2023-11-20 04:00:00": {"1. open": "13.0500", "2. high": "13.0900", "3. low": "13.0000", "4. close": "13.0900", "5. volume": "946"}, "2023-11-17 19:00:00": {"1. open": "13.0300", "2. high": "13.0600", "3. low": "13.0000", "4. close": "13.0100", "5. volume": "299514"}, "2023-11-17 18:00:00": {"1. open": "12.9900", "2. high": "13.0500", "3. low": "12.9800", "4. close": "13.0400", "5. volume": "301628"}, "2023-11-17 17:00:00": {"1. open": "13.0200", "2. high": "13.0300", "3. low": "12.9800", "4. close": "12.9900", "5. volume": "45347"}, "2023-11-17 16:00:00": {"1. open": "13.0400", "2. high": "13.0400", "3. low": "13.0000", "4. close": "13.0200", "5. volume": "924906"}, "2023-11-17 15:00:00": {"1. open": "13.0130", "2. high": "13.0550", "3. low": "12.9300", "4. close": "13.0400", "5. volume": "750679"}, "2023-11-17 14:00:00": {"1. open": "12.9750", "2. high": "13.0200", "3. low": "12.9200", "4. close": "13.0100", "5. volume": "244505"}, "2023-11-17 13:00:00": {"1. open": "12.9800", "2. high": "13.0000", "3. low": "12.9250", "4. close": "12.9750", "5. volume": "286297"}, "2023-11-17 12:00:00": {"1. open": "12.7500", "2. high": "12.9900", "3. low": "12.7500", "4. close": "12.9900", "5. volume": "349146"}, "2023-11-17 11:00:00": {"1. open": "12.9000", "2. high": "12.9000", "3. low": "12.6650", "4. close": "12.7500", "5. volume": "277768"}, "2023-11-17 10:00:00": {"1. open": "12.6400", "2. high": "12.9850", "3. low": "12.5700", "4. close": "12.9000", "5. volume": "704582"}, "2023-11-17 09:00:00": {"1. open": "12.6000", "2. high": "12.7600", "3. low": "12.5200", "4. close": "12.6400", "5. volume": "407644"}, "2023-11-17 08:00:00": {"1. open": "12.6800", "2. high": "12.7500", "3. low": "12.5600", "4. close": "12.6000", "5. volume": "11317"}, "2023-11-17 07:00:00": {"1. open": "12.6500", "2. high": "12.7400", "3. low": "12.6500", "4. close": "12.6900", "5. volume": "2811"}, "2023-11-17 06:00:00": {"1. open": "12.6500", "2. high": "12.6800", "3. low": "12.5400", "4. close": "12.6100", "5. volume": "719"}, "2023-11-17 05:00:00": {"1. open": "12.6700", "2. high": "12.6700", "3. low": "12.6500", "4. close": "12.6700", "5. volume": "265"}, "2023-11-17 04:00:00": {"1. open": "12.5800", "2. high": "12.6600", "3. low": "12.5000", "4. close": "12.6600", "5. volume": "588"}, "2023-11-16 19:00:00": {"1. open": "12.5300", "2. high": "12.6100", "3. low": "12.5300", "4. close": "12.5600", "5. volume": "237059"}, "2023-11-16 18:00:00": {"1. open": "12.5400", "2. high": "12.6100", "3. low": "12.5300", "4. close": "12.6000", "5. volume": "235535"}, "2023-11-16 17:00:00": {"1. open": "12.6300", "2. high": "12.7000", "3. low": "12.5700", "4. close": "12.5700", "5. volume": "5369"}, "2023-11-16 16:00:00": {"1. open": "12.5400", "2. high": "12.6300", "3. low": "12.5300", "4. close": "12.6300", "5. volume": "720357"}, "2023-11-16 15:00:00": {"1. open": "12.6000", "2. high": "12.6100", "3. low": "12.5300", "4. close": "12.5300", "5. volume": "935243"}, "2023-11-16 14:00:00": {"1. open": "12.5300", "2. high": "12.5950", "3. low": "12.5200", "4. close": "12.5950", "5. volume": "226220"}, "2023-11-16 13:00:00": {"1. open": "12.6700", "2. high": "12.6900", "3. low": "12.5200", "4. close": "12.5350", "5. volume": "218780"}, "2023-11-16 12:00:00": {"1. open": "12.6500", "2. high": "12.7100", "3. low": "12.5600", "4. close": "12.6700", "5. volume": "407122"}, "2023-11-16 11:00:00": {"1. open": "12.6100", "2. high": "12.7270", "3. low": "12.5800", "4. close": "12.6450", "5. volume": "218895"}, "2023-11-16 10:00:00": {"1. open": "12.7700", "2. high": "12.7990", "3. low": "12.5700", "4. close": "12.6050", "5. volume": "714005"}, "2023-11-16 09:00:00": {"1. open": "13.2080", "2. high": "13.2500", "3. low": "12.7400", "4. close": "12.7800", "5. volume": "438098"}, "2023-11-16 08:00:00": {"1. open": "13.1300", "2. high": "13.2650", "3. low": "13.1000", "4. close": "13.2100", "5. volume": "3267"}, "2023-11-16 07:00:00": {"1. open": "13.2000", "2. high": "13.2500", "3. low": "13.1300", "4. close": "13.1500", "5. volume": "2017"}, "2023-11-16 06:00:00": {"1. open": "13.1600", "2. high": "13.2400", "3. low": "13.1600", "4. close": "13.2400", "5. volume": "1973"}, "2023-11-16 05:00:00": {"1. open": "13.1800", "2. high": "13.2100", "3. low": "13.1500", "4. close": "13.1800", "5. volume": "703"}, "2023-11-16 04:00:00": {"1. open": "13.1400", "2. high": "13.2700", "3. low": "13.1400", "4. close": "13.1900", "5. volume": "209"}, "2023-11-15 19:00:00": {"1. open": "13.2700", "2. high": "13.2800", "3. low": "13.2000", "4. close": "13.2400", "5. volume": "224332"}, "2023-11-15 18:00:00": {"1. open": "13.2000", "2. high": "13.2800", "3. low": "13.2000", "4. close": "13.2700", "5. volume": "223548"}, "2023-11-15 17:00:00": {"1. open": "13.2300", "2. high": "13.2800", "3. low": "13.1500", "4. close": "13.2500", "5. volume": "3924"}, "2023-11-15 16:00:00": {"1. open": "13.2700", "2. high": "13.2800", "3. low": "13.2200", "4. close": "13.2300", "5. volume": "724518"}, "2023-11-15 15:00:00": {"1. open": "13.2300", "2. high": "13.3000", "3. low": "13.2100", "4. close": "13.2800", "5. volume": "602053"}, "2023-11-15 14:00:00": {"1. open": "13.2150", "2. high": "13.2800", "3. low": "13.1600", "4. close": "13.2350", "5. volume": "265587"}, "2023-11-15 13:00:00": {"1. open": "13.1900", "2. high": "13.2200", "3. low": "13.0300", "4. close": "13.2100", "5. volume": "261522"}, "2023-11-15 12:00:00": {"1. open": "13.1150", "2. high": "13.3150", "3. low": "13.1040", "4. close": "13.1950", "5. volume": "505130"}, "2023-11-15 11:00:00": {"1. open": "13.3650", "2. high": "13.4050", "3. low": "13.1000", "4. close": "13.1100", "5. volume": "539445"}, "2023-11-15 10:00:00": {"1. open": "13.1700", "2. high": "13.4500", "3. low": "13.1000", "4. close": "13.3700", "5. volume": "875393"}, "2023-11-15 09:00:00": {"1. open": "13.1000", "2. high": "13.5000", "3. low": "12.9600", "4. close": "13.1600", "5. volume": "706337"}, "2023-11-15 08:00:00": {"1. open": "13.4200", "2. high": "13.5030", "3. low": "12.9400", "4. close": "13.1000", "5. volume": "44509"}, "2023-11-15 07:00:00": {"1. open": "13.4300", "2. high": "13.4300", "3. low": "13.2200", "4. close": "13.2200", "5. volume": "10231"}, "2023-11-15 06:00:00": {"1. open": "13.4000", "2. high": "13.4900", "3. low": "13.3700", "4. close": "13.4300", "5. volume": "5668"}, "2023-11-15 05:00:00": {"1. open": "13.1900", "2. high": "14.0000", "3. low": "13.1500", "4. close": "13.3900", "5. volume": "14021"}, "2023-11-15 04:00:00": {"1. open": "12.9900", "2. high": "13.3200", "3. low": "12.9600", "4. close": "13.1200", "5. volume": "1847"}, "2023-11-14 19:00:00": {"1. open": "12.9000", "2. high": "12.9500", "3. low": "12.8300", "4. close": "12.8900", "5. volume": "237079"}, "2023-11-14 18:00:00": {"1. open": "12.8300", "2. high": "12.9000", "3. low": "12.8300", "4. close": "12.8530", "5. volume": "235037"}, "2023-11-14 17:00:00": {"1. open": "12.9000", "2. high": "12.9000", "3. low": "12.8200", "4. close": "12.8700", "5. volume": "2768"}, "2023-11-14 16:00:00": {"1. open": "12.9000", "2. high": "12.9980", "3. low": "12.8200", "4. close": "12.8700", "5. volume": "725363"}, "2023-11-14 15:00:00": {"1. open": "12.9700", "2. high": "13.0400", "3. low": "12.9000", "4. close": "12.9000", "5. volume": "1025285"}, "2023-11-14 14:00:00": {"1. open": "12.9300", "2. high": "12.9600", "3. low": "12.8200", "4. close": "12.9600", "5. volume": "405780"}, "2023-11-14 13:00:00": {"1. open": "13.0100", "2. high": "13.0350", "3. low": "12.9200", "4. close": "12.9370", "5. volume": "372215"}, "2023-11-14 12:00:00": {"1. open": "13.0650", "2. high": "13.1000", "3. low": "12.9400", "4. close": "13.0100", "5. volume": "435450"}, "2023-11-14 11:00:00": {"1. open": "13.1550", "2. high": "13.3000", "3. low": "13.0600", "4. close": "13.0700", "5. volume": "614902"}, "2023-11-14 10:00:00": {"1. open": "13.0050", "2. high": "13.2800", "3. low": "12.9150", "4. close": "13.1500", "5. volume": "697574"}, "2023-11-14 09:00:00": {"1. open": "12.5300", "2. high": "13.3900", "3. low": "12.5000", "4. close": "13.0000", "5. volume": "1305718"}, "2023-11-14 08:00:00": {"1. open": "12.2900", "2. high": "12.6600", "3. low": "12.1480", "4. close": "12.5300", "5. volume": "61272"}, "2023-11-14 07:00:00": {"1. open": "12.2600", "2. high": "12.2700", "3. low": "12.2000", "4. close": "12.2400", "5. volume": "1406"}, "2023-11-14 06:00:00": {"1. open": "12.2000", "2. high": "12.3100", "3. low": "12.1600", "4. close": "12.2600", "5. volume": "3742"}, "2023-11-14 05:00:00": {"1. open": "12.2000", "2. high": "12.3200", "3. low": "12.1900", "4. close": "12.2000", "5. volume": "3281"}, "2023-11-14 04:00:00": {"1. open": "12.4000", "2. high": "12.4000", "3. low": "12.1600", "4. close": "12.2000", "5. volume": "1223"}, "2023-11-13 19:00:00": {"1. open": "12.1400", "2. high": "12.2600", "3. low": "12.1400", "4. close": "12.1700", "5. volume": "252053"}, "2023-11-13 18:00:00": {"1. open": "12.3000", "2. high": "12.3000", "3. low": "12.1400", "4. close": "12.1700", "5. volume": "253415"}, "2023-11-13 17:00:00": {"1. open": "12.1800", "2. high": "12.3000", "3. low": "12.1600", "4. close": "12.2900", "5. volume": "8503"}, "2023-11-13 16:00:00": {"1. open": "12.1400", "2. high": "12.1900", "3. low": "12.1400", "4. close": "12.1800", "5. volume": "759554"}, "2023-11-13 15:00:00": {"1. open": "12.0300", "2. high": "12.2700", "3. low": "12.0100", "4. close": "12.1500", "5. volume": "1015296"}, "2023-11-13 14:00:00": {"1. open": "12.0100", "2. high": "12.0500", "3. low": "11.9800", "4. close": "12.0350", "5. volume": "309489"}, "2023-11-13 13:00:00": {"1. open": "12.0100", "2. high": "12.0700", "3. low": "11.9600", "4. close": "12.0000", "5. volume": "275993"}, "2023-11-13 12:00:00": {"1. open": "12.1500", "2. high": "12.1600", "3. low": "11.9790", "4. close": "12.0100", "5. volume": "297631"}, "2023-11-13 11:00:00": {"1. open": "11.9750", "2. high": "12.1600", "3. low": "11.9700", "4. close": "12.1450", "5. volume": "471960"}, "2023-11-13 10:00:00": {"1. open": "12.0010", "2. high": "12.0800", "3. low": "11.8250", "4. close": "11.9790", "5. volume": "945942"}, "2023-11-13 09:00:00": {"1. open": "12.5400", "2. high": "12.8350", "3. low": "11.9850", "4. close": "12.0150", "5. volume": "713075"}, "2023-11-13 08:00:00": {"1. open": "12.6000", "2. high": "12.7000", "3. low": "12.4300", "4. close": "12.5500", "5. volume": "11832"}, "2023-11-13 07:00:00": {"1. open": "12.6800", "2. high": "12.6800", "3. low": "12.6000", "4. close": "12.6300", "5. volume": "2481"}, "2023-11-13 06:00:00": {"1. open": "12.6300", "2. high": "12.6800", "3. low": "12.6300", "4. close": "12.6500", "5. volume": "416"}, "2023-11-13 05:00:00": {"1. open": "12.6600", "2. high": "12.6600", "3. low": "12.5900", "4. close": "12.6600", "5. volume": "340"}, "2023-11-13 04:00:00": {"1. open": "12.6100", "2. high": "12.7100", "3. low": "12.5500", "4. close": "12.6600", "5. volume": "1931"}, "2023-11-10 19:00:00": {"1. open": "12.5400", "2. high": "12.7700", "3. low": "12.5300", "4. close": "12.7000", "5. volume": "233098"}, "2023-11-10 18:00:00": {"1. open": "12.5700", "2. high": "12.5700", "3. low": "12.5400", "4. close": "12.5500", "5. volume": "232427"}, "2023-11-10 17:00:00": {"1. open": "12.5500", "2. high": "12.5700", "3. low": "12.5200", "4. close": "12.5700", "5. volume": "2682"}, "2023-11-10 16:00:00": {"1. open": "12.5500", "2. high": "12.7700", "3. low": "12.5400", "4. close": "12.5500", "5. volume": "706831"}, "2023-11-10 15:00:00": {"1. open": "12.6330", "2. high": "12.6450", "3. low": "12.5400", "4. close": "12.5450", "5. volume": "738633"}, "2023-11-10 14:00:00": {"1. open": "12.6850", "2. high": "12.7650", "3. low": "12.6200", "4. close": "12.6390", "5. volume": "220996"}, "2023-11-10 13:00:00": {"1. open": "12.7300", "2. high": "12.8050", "3. low": "12.6100", "4. close": "12.6900", "5. volume": "307024"}, "2023-11-10 12:00:00": {"1. open": "12.5100", "2. high": "12.8300", "3. low": "12.4800", "4. close": "12.7300", "5. volume": "395769"}, "2023-11-10 11:00:00": {"1. open": "12.6000", "2. high": "12.6780", "3. low": "12.5050", "4. close": "12.5150", "5. volume": "308042"}, "2023-11-10 10:00:00": {"1. open": "12.8300", "2. high": "12.9700", "3. low": "12.4700", "4. close": "12.5900", "5. volume": "751550"}, "2023-11-10 09:00:00": {"1. open": "12.9100", "2. high": "12.9800", "3. low": "12.3500", "4. close": "12.8350", "5. volume": "887035"}, "2023-11-10 08:00:00": {"1. open": "12.8100", "2. high": "12.9500", "3. low": "12.7100", "4. close": "12.9100", "5. volume": "8611"}, "2023-11-10 07:00:00": {"1. open": "12.8200", "2. high": "12.8200", "3. low": "12.7800", "4. close": "12.8000", "5. volume": "966"}, "2023-11-10 06:00:00": {"1. open": "12.8400", "2. high": "12.8600", "3. low": "12.7800", "4. close": "12.8100", "5. volume": "2101"}, "2023-11-10 05:00:00": {"1. open": "12.8100", "2. high": "12.8600", "3. low": "12.7600", "4. close": "12.8500", "5. volume": "136"}, "2023-11-10 04:00:00": {"1. open": "12.7200", "2. high": "12.8800", "3. low": "12.7200", "4. close": "12.8500", "5. volume": "2698"}, "2023-11-09 19:00:00": {"1. open": "12.7000", "2. high": "12.7800", "3. low": "12.7000", "4. close": "12.7800", "5. volume": "278528"}, "2023-11-09 18:00:00": {"1. open": "12.7900", "2. high": "12.8000", "3. low": "12.7000", "4. close": "12.7600", "5. volume": "275205"}, "2023-11-09 17:00:00": {"1. open": "12.7500", "2. high": "12.8000", "3. low": "12.7300", "4. close": "12.7800", "5. volume": "2369"}, "2023-11-09 16:00:00": {"1. open": "12.7200", "2. high": "12.9500", "3. low": "12.7000", "4. close": "12.7500", "5. volume": "838341"}, "2023-11-09 15:00:00": {"1. open": "12.7700", "2. high": "12.7900", "3. low": "12.7000", "4. close": "12.7200", "5. volume": "662245"}, "2023-11-09 14:00:00": {"1. open": "12.8000", "2. high": "12.8650", "3. low": "12.7550", "4. close": "12.7750", "5. volume": "222477"}, "2023-11-09 13:00:00": {"1. open": "13.0250", "2. high": "13.0350", "3. low": "12.7900", "4. close": "12.8090", "5. volume": "479646"}, "2023-11-09 12:00:00": {"1. open": "13.0600", "2. high": "13.0900", "3. low": "12.9600", "4. close": "13.0200", "5. volume": "187203"}, "2023-11-09 11:00:00": {"1. open": "13.1000", "2. high": "13.1050", "3. low": "12.9800", "4. close": "13.0650", "5. volume": "270588"}, "2023-11-09 10:00:00": {"1. open": "13.2250", "2. high": "13.2300", "3. low": "13.0600", "4. close": "13.1000", "5. volume": "308431"}, "2023-11-09 09:00:00": {"1. open": "13.3500", "2. high": "13.4200", "3. low": "13.1100", "4. close": "13.2200", "5. volume": "297296"}, "2023-11-09 08:00:00": {"1. open": "13.3710", "2. high": "13.4300", "3. low": "13.2000", "4. close": "13.3490", "5. volume": "21038"}, "2023-11-09 07:00:00": {"1. open": "13.3900", "2. high": "13.3900", "3. low": "13.3500", "4. close": "13.3700", "5. volume": "1031"}, "2023-11-09 06:00:00": {"1. open": "13.3700", "2. high": "13.4000", "3. low": "13.3300", "4. close": "13.3900", "5. volume": "324"}, "2023-11-09 05:00:00": {"1. open": "13.3700", "2. high": "13.4100", "3. low": "13.3500", "4. close": "13.3500", "5. volume": "40"}, "2023-11-09 04:00:00": {"1. open": "13.2600", "2. high": "13.3600", "3. low": "13.2300", "4. close": "13.3400", "5. volume": "69"}, "2023-11-08 19:00:00": {"1. open": "13.2800", "2. high": "13.2800", "3. low": "13.2200", "4. close": "13.2500", "5. volume": "150299"}, "2023-11-08 18:00:00": {"1. open": "13.2400", "2. high": "13.3300", "3. low": "13.2200", "4. close": "13.2700", "5. volume": "150624"}, "2023-11-08 17:00:00": {"1. open": "13.2950", "2. high": "13.3300", "3. low": "13.2100", "4. close": "13.2600", "5. volume": "4835"}, "2023-11-08 16:00:00": {"1. open": "13.2800", "2. high": "13.5200", "3. low": "13.2100", "4. close": "13.3200", "5. volume": "480619"}, "2023-11-08 15:00:00": {"1. open": "13.3900", "2. high": "13.4300", "3. low": "13.2800", "4. close": "13.2800", "5. volume": "409203"}, "2023-11-08 14:00:00": {"1. open": "13.4500", "2. high": "13.4900", "3. low": "13.3900", "4. close": "13.3900", "5. volume": "105346"}, "2023-11-08 13:00:00": {"1. open": "13.4200", "2. high": "13.4670", "3. low": "13.3350", "4. close": "13.4480", "5. volume": "160039"}, "2023-11-08 12:00:00": {"1. open": "13.5000", "2. high": "13.5700", "3. low": "13.4150", "4. close": "13.4200", "5. volume": "152250"}, "2023-11-08 11:00:00": {"1. open": "13.4950", "2. high": "13.5650", "3. low": "13.4600", "4. close": "13.5000", "5. volume": "99470"}, "2023-11-08 10:00:00": {"1. open": "13.6600", "2. high": "13.7000", "3. low": "13.4250", "4. close": "13.5020", "5. volume": "317349"}, "2023-11-08 09:00:00": {"1. open": "13.7000", "2. high": "13.7600", "3. low": "13.4600", "4. close": "13.6500", "5. volume": "258398"}, "2023-11-08 08:00:00": {"1. open": "13.6910", "2. high": "13.8000", "3. low": "13.6350", "4. close": "13.7200", "5. volume": "5340"}, "2023-11-08 07:00:00": {"1. open": "13.7200", "2. high": "13.7500", "3. low": "13.7000", "4. close": "13.7100", "5. volume": "544"}, "2023-11-08 06:00:00": {"1. open": "13.7600", "2. high": "13.7800", "3. low": "13.7200", "4. close": "13.7200", "5. volume": "1103"}, "2023-11-08 05:00:00": {"1. open": "13.6600", "2. high": "13.8100", "3. low": "13.6400", "4. close": "13.7600", "5. volume": "1468"}, "2023-11-08 04:00:00": {"1. open": "13.6800", "2. high": "13.8000", "3. low": "13.6300", "4. close": "13.6300", "5. volume": "132"}, "2023-11-07 19:00:00": {"1. open": "13.6400", "2. high": "13.7000", "3. low": "13.6200", "4. close": "13.6700", "5. volume": "100204"}, "2023-11-07 18:00:00": {"1. open": "13.6400", "2. high": "13.7000", "3. low": "13.6200", "4. close": "13.6200", "5. volume": "100240"}, "2023-11-07 17:00:00": {"1. open": "13.6520", "2. high": "13.7100", "3. low": "13.6200", "4. close": "13.6950", "5. volume": "718"}, "2023-11-07 16:00:00": {"1. open": "13.6400", "2. high": "13.7300", "3. low": "13.5600", "4. close": "13.7000", "5. volume": "308713"}, "2023-11-07 15:00:00": {"1. open": "13.6950", "2. high": "13.7900", "3. low": "13.6300", "4. close": "13.6400", "5. volume": "476032"}, "2023-11-07 14:00:00": {"1. open": "13.5400", "2. high": "13.7000", "3. low": "13.5400", "4. close": "13.7000", "5. volume": "233135"}, "2023-11-07 13:00:00": {"1. open": "13.4850", "2. high": "13.5900", "3. low": "13.4500", "4. close": "13.5300", "5. volume": "224522"}, "2023-11-07 12:00:00": {"1. open": "13.6100", "2. high": "13.6200", "3. low": "13.4600", "4. close": "13.4850", "5. volume": "142382"}, "2023-11-07 11:00:00": {"1. open": "13.5850", "2. high": "13.7300", "3. low": "13.5300", "4. close": "13.6050", "5. volume": "264679"}, "2023-11-07 10:00:00": {"1. open": "13.3800", "2. high": "13.7400", "3. low": "13.2710", "4. close": "13.5900", "5. volume": "610118"}, "2023-11-07 09:00:00": {"1. open": "13.5400", "2. high": "13.5870", "3. low": "13.2300", "4. close": "13.3750", "5. volume": "283752"}, "2023-11-07 08:00:00": {"1. open": "13.4500", "2. high": "13.8200", "3. low": "13.4000", "4. close": "13.5600", "5. volume": "6110"}, "2023-11-07 07:00:00": {"1. open": "13.4400", "2. high": "13.5300", "3. low": "13.4050", "4. close": "13.5200", "5. volume": "3824"}, "2023-11-07 06:00:00": {"1. open": "13.6100", "2. high": "13.6200", "3. low": "13.4300", "4. close": "13.4300", "5. volume": "1420"}, "2023-11-07 05:00:00": {"1. open": "13.5500", "2. high": "13.6100", "3. low": "13.5200", "4. close": "13.5700", "5. volume": "145"}, "2023-11-07 04:00:00": {"1. open": "13.5000", "2. high": "13.5900", "3. low": "13.5000", "4. close": "13.5900", "5. volume": "152"}, "2023-11-06 19:00:00": {"1. open": "13.5300", "2. high": "13.5400", "3. low": "13.4900", "4. close": "13.5300", "5. volume": "196367"}, "2023-11-06 18:00:00": {"1. open": "13.4100", "2. high": "13.5300", "3. low": "13.4100", "4. close": "13.5200", "5. volume": "192911"}, "2023-11-06 17:00:00": {"1. open": "13.5190", "2. high": "13.5300", "3. low": "13.4100", "4. close": "13.4100", "5. volume": "4061"}, "2023-11-06 16:00:00": {"1. open": "13.5350", "2. high": "13.6500", "3. low": "13.5000", "4. close": "13.5200", "5. volume": "589179"}, "2023-11-06 15:00:00": {"1. open": "13.5800", "2. high": "13.6100", "3. low": "13.5100", "4. close": "13.5300", "5. volume": "474176"}, "2023-11-06 14:00:00": {"1. open": "13.5390", "2. high": "13.6300", "3. low": "13.4850", "4. close": "13.5710", "5. volume": "164128"}, "2023-11-06 13:00:00": {"1. open": "13.6550", "2. high": "13.6600", "3. low": "13.5200", "4. close": "13.5350", "5. volume": "182848"}, "2023-11-06 12:00:00": {"1. open": "13.7690", "2. high": "13.7800", "3. low": "13.6450", "4. close": "13.6590", "5. volume": "155756"}, "2023-11-06 11:00:00": {"1. open": "13.8750", "2. high": "13.8790", "3. low": "13.6520", "4. close": "13.7650", "5. volume": "230453"}, "2023-11-06 10:00:00": {"1. open": "13.8000", "2. high": "13.9800", "3. low": "13.7250", "4. close": "13.8710", "5. volume": "385924"}, "2023-11-06 09:00:00": {"1. open": "13.9650", "2. high": "14.0450", "3. low": "13.7900", "4. close": "13.8000", "5. volume": "322702"}, "2023-11-06 08:00:00": {"1. open": "13.8900", "2. high": "14.2800", "3. low": "13.8000", "4. close": "13.9600", "5. volume": "17825"}, "2023-11-06 07:00:00": {"1. open": "13.9800", "2. high": "14.0600", "3. low": "13.9000", "4. close": "14.0300", "5. volume": "9322"}, "2023-11-06 06:00:00": {"1. open": "13.9900", "2. high": "14.0500", "3. low": "13.9900", "4. close": "13.9900", "5. volume": "362"}, "2023-11-06 05:00:00": {"1. open": "14.0400", "2. high": "14.0800", "3. low": "13.9800", "4. close": "13.9800", "5. volume": "2576"}, "2023-11-06 04:00:00": {"1. open": "13.9400", "2. high": "14.2800", "3. low": "13.8600", "4. close": "14.0800", "5. volume": "2563"}, "2023-11-03 19:00:00": {"1. open": "13.8700", "2. high": "13.9700", "3. low": "13.8700", "4. close": "13.8900", "5. volume": "116529"}, "2023-11-03 18:00:00": {"1. open": "13.9400", "2. high": "14.1000", "3. low": "13.8700", "4. close": "13.8800", "5. volume": "116882"}, "2023-11-03 17:00:00": {"1. open": "13.8700", "2. high": "14.1000", "3. low": "13.8200", "4. close": "13.9500", "5. volume": "5346"}, "2023-11-03 16:00:00": {"1. open": "13.8650", "2. high": "13.9200", "3. low": "13.8650", "4. close": "13.8900", "5. volume": "354194"}, "2023-11-03 15:00:00": {"1. open": "14.0050", "2. high": "14.0050", "3. low": "13.8310", "4. close": "13.8650", "5. volume": "461838"}, "2023-11-03 14:00:00": {"1. open": "13.8950", "2. high": "14.0700", "3. low": "13.8400", "4. close": "14.0100", "5. volume": "225399"}, "2023-11-03 13:00:00": {"1. open": "14.0420", "2. high": "14.0450", "3. low": "13.8500", "4. close": "13.8900", "5. volume": "304171"}, "2023-11-03 12:00:00": {"1. open": "14.0900", "2. high": "14.0900", "3. low": "13.9900", "4. close": "14.0450", "5. volume": "237685"}, "2023-11-03 11:00:00": {"1. open": "14.2200", "2. high": "14.2350", "3. low": "14.0050", "4. close": "14.0850", "5. volume": "294382"}, "2023-11-03 10:00:00": {"1. open": "14.3100", "2. high": "14.3300", "3. low": "14.1300", "4. close": "14.2180", "5. volume": "559037"}, "2023-11-03 09:00:00": {"1. open": "13.7000", "2. high": "14.4000", "3. low": "13.6930", "4. close": "14.2700", "5. volume": "738804"}, "2023-11-03 08:00:00": {"1. open": "13.6400", "2. high": "13.8000", "3. low": "13.5900", "4. close": "13.7200", "5. volume": "6355"}, "2023-11-03 07:00:00": {"1. open": "13.6400", "2. high": "13.7100", "3. low": "13.6100", "4. close": "13.7000", "5. volume": "1475"}, "2023-11-03 06:00:00": {"1. open": "13.6200", "2. high": "13.6400", "3. low": "13.6000", "4. close": "13.6300", "5. volume": "911"}, "2023-11-03 05:00:00": {"1. open": "13.6200", "2. high": "13.6400", "3. low": "13.5900", "4. close": "13.6100", "5. volume": "278"}, "2023-11-03 04:00:00": {"1. open": "13.7000", "2. high": "13.7500", "3. low": "13.5900", "4. close": "13.6200", "5. volume": "441"}}}